MANIFEST.in
arrayterator.py
ez_setup.py
setup.cfg
setup.py
arrayterator.egg-info/PKG-INFO
arrayterator.egg-info/SOURCES.txt
arrayterator.egg-info/dependency_links.txt
arrayterator.egg-info/entry_points.txt
arrayterator.egg-info/top_level.txt
arrayterator.egg-info/zip-safe
tests/test_stochastic.py
tests/test_stochastic.pyc