Metadata-Version: 1.0
Name: arrayterator
Version: 1.0.1
Summary: Buffered iterator for big arrays.
Home-page: http://taoetc.org/6
Author: Roberto De Almeida
Author-email: rob@pydap.org
License: MIT
Download-URL: http://cheeseshop.python.org/packages/source/a/arrayterator/arrayterator-1.0.1.tar.gz
Keywords: data array math
Platform: UNKNOWN
Classifier: Development Status :: 4 - Beta
Classifier: Environment :: Console
Classifier: Intended Audience :: Developers
Classifier: Intended Audience :: Science/Research
Classifier: License :: OSI Approved :: MIT License
Classifier: Operating System :: OS Independent
Classifier: Programming Language :: Python
Classifier: Topic :: Scientific/Engineering
Classifier: Topic :: Software Development :: Libraries :: Python Modules
